taysai/__init__.py
taysai/model_utils.py
taysai-0.1.2.dist-info/METADATA
taysai-0.1.2.dist-info/WHEEL
taysai-0.1.2.dist-info/top_level.txt
taysai-0.1.2.dist-info/RECORD
