Metadata-Version: 2.1
Name: taysai
Version: 0.1.2
Summary: A utility package for saving PyTorch models with automatic import detection.
Home-page: https://github.com/yourusername/taysai
Author: Taylor
Author-email: your-email@example.com
License: UNKNOWN
Platform: UNKNOWN
Classifier: Programming Language :: Python :: 3
Classifier: License :: OSI Approved :: MIT License
Classifier: Operating System :: OS Independent
Requires-Python: >=3.6
Requires-Dist: dill
Requires-Dist: torch
